{
  "modules": {
    "server.gemini_live": {
      "data_targets": {},
      "entrypoint": false,
      "external_imports": [
        "asyncio",
        "google",
        "inspect",
        "logging"
      ],
      "internal_imports": [],
      "package": "server",
      "path": "server/gemini_live.py",
      "public_symbols": [
        "GeminiLive",
        "receive_loop",
        "send_audio",
        "send_outgoing",
        "send_text",
        "send_video",
        "start_session"
      ]
    },
    "server.main": {
      "data_targets": {},
      "entrypoint": true,
      "external_imports": [
        "argparse",
        "asyncio",
        "base64",
        "contextlib",
        "dotenv",
        "fastapi",
        "gemini_live",
        "json",
        "logging",
        "os",
        "pathlib",
        "progress_tracker",
        "uvicorn"
      ],
      "internal_imports": [],
      "package": "server",
      "path": "server/main.py",
      "public_symbols": [
        "audio_interrupt_callback",
        "audio_output_callback",
        "clear_queue",
        "configure_logging",
        "eval_frontend",
        "get_recipe_config",
        "knowledge_item",
        "knowledge_list",
        "load_knowledge_entries",
        "parse_optional_int_env",
        "progress",
        "put_realtime",
        "receive_from_client",
        "root",
        "run_session",
        "start_model_session_if_needed",
        "websocket_endpoint"
      ]
    },
    "server.progress_tracker": {
      "data_targets": {},
      "entrypoint": true,
      "external_imports": [
        "collections",
        "copy",
        "re",
        "threading",
        "time"
      ],
      "internal_imports": [],
      "package": "server",
      "path": "server/progress_tracker.py",
      "public_symbols": [
        "PastaProgressMemory",
        "ProgressStateStore",
        "RecipeProgressMemory",
        "build_checkpoint_message",
        "build_checkpoint_text",
        "get",
        "observe_user_turn",
        "set",
        "set_from_memory",
        "to_progress_payload"
      ]
    },
    "server.tests.test_gemini_live": {
      "data_targets": {},
      "entrypoint": true,
      "external_imports": [
        "asyncio",
        "gemini_live",
        "pathlib",
        "sys"
      ],
      "internal_imports": [],
      "package": "server",
      "path": "server/tests/test_gemini_live.py",
      "public_symbols": [
        "FakeAio",
        "FakeClient",
        "FakeConnectContext",
        "FakeLive",
        "FakeSession",
        "connect",
        "receive",
        "receive_impl",
        "receive_impl",
        "receive_impl",
        "receive_impl",
        "receive_impl",
        "send",
        "send_realtime_input",
        "send_tool_response",
        "test_init_omits_http_options_when_api_version_is_none",
        "test_init_strips_vertex_model_prefix_and_applies_api_version",
        "test_start_session_applies_live_config",
        "test_start_session_enables_adaptive_compression_by_default",
        "test_start_session_yields_error_event_when_receive_fails"
      ]
    },
    "server.tests.test_main_logging": {
      "data_targets": {},
      "entrypoint": false,
      "external_imports": [
        "importlib",
        "logging",
        "pathlib",
        "sys"
      ],
      "internal_imports": [],
      "package": "server",
      "path": "server/tests/test_main_logging.py",
      "public_symbols": [
        "test_configure_logging_sets_debug_level"
      ]
    },
    "server.tests.test_main_memory": {
      "data_targets": {},
      "entrypoint": false,
      "external_imports": [
        "importlib",
        "pathlib",
        "sys"
      ],
      "internal_imports": [],
      "package": "server",
      "path": "server/tests/test_main_memory.py",
      "public_symbols": [
        "test_pasta_memory_advances_when_step_completed",
        "test_pasta_memory_deduplicates_same_signature",
        "test_pasta_memory_initial_checkpoint",
        "test_pasta_memory_progress_payload_statuses"
      ]
    },
    "server.tests.test_main_routes": {
      "data_targets": {},
      "entrypoint": true,
      "external_imports": [
        "fastapi",
        "importlib",
        "pathlib",
        "sys"
      ],
      "internal_imports": [],
      "package": "server",
      "path": "server/tests/test_main_routes.py",
      "public_symbols": [
        "test_eval_serves_existing_frontend",
        "test_knowledge_item_returns_prompt_and_steps",
        "test_knowledge_list_includes_expected_recipes",
        "test_root_serves_ar_frontend"
      ]
    },
    "server.tests.test_main_websocket": {
      "data_targets": {},
      "entrypoint": false,
      "external_imports": [
        "asyncio",
        "fastapi",
        "importlib",
        "json",
        "logging",
        "pathlib",
        "sys"
      ],
      "internal_imports": [],
      "package": "server",
      "path": "server/tests/test_main_websocket.py",
      "public_symbols": [
        "start_session",
        "test_ws_disconnect_does_not_log_receive_after_disconnect_error",
        "test_ws_ready_and_start_session_handshake",
        "test_ws_start_session_uses_selected_recipe"
      ]
    }
  }
}
